{
  "definition": {
    "field": "pointer",
    "text": "Select",
    "title": "Insert a definition for a select component",
    "value": {
      "component": {
        "configuration": {
          "dataSet": [
            {"name": "Option 1", "value": "option-1", "disabled": false},
            {"name": "Option 2", "value": "option-2", "disabled": false},
            {"name": "Option 3", "value": "option-3", "disabled": false}
          ],
          "multiple": false
        },
        "type": "select"
      }
    }
  },
  "schema": {
    "type": "string"
  }
}
